{"nodes": [{"id": "templates_coturn_deployment", "label": "coturn Deployment", "file_type": "code", "source_file": "deploy/helm/dograh/templates/coturn-deployment.yaml", "source_location": null, "source_url": null, "captured_at": null, "author": null, "contributor": null, "rationale": "Singleton per-LB; HA TURN needs multiple LBs. TURN_SECRET via CLI from Secret."}], "edges": [{"source": "templates_coturn_deployment", "target": "templates_coturn_configmap", "relation": "references", "confidence": "EXTRACTED", "confidence_score": 1.0, "source_file": "deploy/helm/dograh/templates/coturn-deployment.yaml", "source_location": null, "weight": 1.0}], "hyperedges": []}